st_diff_viewer/__init__.py
st_diff_viewer/frontend/out/404.html
st_diff_viewer/frontend/out/_next/static/R8-sZqhKigDxjwG4kYFvh/_buildManifest.js
st_diff_viewer/frontend/out/_next/static/R8-sZqhKigDxjwG4kYFvh/_ssgManifest.js
st_diff_viewer/frontend/out/_next/static/chunks/589-8d139740f609832d.js
st_diff_viewer/frontend/out/_next/static/chunks/framework-c0663f0e1a0e4372.js
st_diff_viewer/frontend/out/_next/static/chunks/main-49701d22161bf8f9.js
st_diff_viewer/frontend/out/_next/static/chunks/pages/_app-2ddf65715eee6393.js
st_diff_viewer/frontend/out/_next/static/chunks/pages/_error-54de1933a164a1ff.js
st_diff_viewer/frontend/out/_next/static/chunks/pages/index-a75592537628c1d9.js
st_diff_viewer/frontend/out/_next/static/chunks/polyfills-78c92fac7aa8fdd8.js
st_diff_viewer/frontend/out/_next/static/chunks/webpack-0b8307be69e3f69a.js
st_diff_viewer/frontend/out/_next/static/css/2ef6db704abbe036.css
st_diff_viewer/frontend/out/favicon.ico
st_diff_viewer/frontend/out/index.html
st_diff_viewer/frontend/out/vercel.svg
st_diff_viewer-1.0.6.dist-info/LICENSE
st_diff_viewer-1.0.6.dist-info/METADATA
st_diff_viewer-1.0.6.dist-info/WHEEL
st_diff_viewer-1.0.6.dist-info/RECORD
